__init__.py
proem.py
proem-1.1.0.dist-info/LICENSE
proem-1.1.0.dist-info/METADATA
proem-1.1.0.dist-info/WHEEL
proem-1.1.0.dist-info/top_level.txt
proem-1.1.0.dist-info/RECORD
